{
  "interactionModel": {
    "languageModel": {
      "invocationName": "ônibus b. h.",
      "intents": [
        {
          "name": "AMAZON.CancelIntent",
          "samples": []
        },
        {
          "name": "AMAZON.HelpIntent",
          "samples": []
        },
        {
          "name": "AMAZON.StopIntent",
          "samples": []
        },
        {
          "name": "AMAZON.NavigateHomeIntent",
          "samples": []
        },
        {
          "name": "AMAZON.FallbackIntent",
          "samples": []
        },
        {
          "name": "SetBusLineIntent",
          "slots": [
            {
              "name": "bus_line_string",
              "type": "AMAZON.SearchQuery"
            }
          ],
          "samples": [
            "número {bus_line_string}",
            "linha número {bus_line_string}",
            "ônibus {bus_line_string}",
            "linha {bus_line_string}"
          ]
        },
        {
          "name": "AMAZON.YesIntent",
          "samples": []
        },
        {
          "name": "AMAZON.NoIntent",
          "samples": []
        },
        {
          "name": "RepeatIntent",
          "slots": [],
          "samples": [
            "fale novamente",
            "fale denovo",
            "repete por favor",
            "repita",
            "repete",
            "repetir"
          ]
        },
        {
          "name": "SetOptionIntent",
          "slots": [
            {
              "name": "option_number",
              "type": "AMAZON.NUMBER"
            }
          ],
          "samples": [
            "{option_number}"
          ]
        },
        {
          "name": "SetOptionOneIntent",
          "slots": [],
          "samples": [
            "opção um",
            "opção um pontos mais próximos",
            "pontos mais próximos",
            "por favor opção um pontos mais próximos",
            "por favor pontos mais próximos",
            "por favor opção um"
          ]
        },
        {
          "name": "SetOptionTwoIntent",
          "slots": [],
          "samples": [
            "opção dois",
            "opção dois estou no ponto de ônibus",
            "estou no ponto de ônibus",
            "por favor opção dois",
            "por favor opção dois estou no ponto de ônibus",
            "por favor estou no ponto de ônibus"
          ]
        },
        {
          "name": "SetOptionThreeIntent",
          "slots": [],
          "samples": [
            "opção três",
            "opção três previsão de parada",
            "previsão de parada",
            "por favor opção três",
            "por favor opção três previsão de parada",
            "por favor previsão de parada"
          ]
        }
      ],
      "types": []
    }
  },
  "version": "14"
}
